setup.py
gf/__init__.py
gf.rejuice.egg-info/PKG-INFO
gf.rejuice.egg-info/SOURCES.txt
gf.rejuice.egg-info/dependency_links.txt
gf.rejuice.egg-info/entry_points.txt
gf.rejuice.egg-info/namespace_packages.txt
gf.rejuice.egg-info/not-zip-safe
gf.rejuice.egg-info/requires.txt
gf.rejuice.egg-info/top_level.txt
gf/rejuice/__init__.py
gf/rejuice/config.py
gf/rejuice/develjuice.py
gf/rejuice/rejuice_script.py
gf/rejuice/resolver.py
gf/rejuice/tests/__init__.py
gf/rejuice/tests/test_configparser.py
gf/rejuice/tests/test_develjuice.py
gf/rejuice/tests/test_rejuice_script.py
gf/rejuice/tests/test_resolver.py
gf/rejuice/tests/utils.py