Metadata-Version: 1.0
Name: gf.rejuice
Version: 0.1
Summary: `gf.rejuice` provides additional tools for developers to use `Juicer` for the compression of Javascript and CSS resources, in the context of python web applications that run via WSGI.
Home-page: http://www.repoze.org
Author: Balazs Ree
Author-email: ree@greenfinity.hu
License: GPL
Keywords: web middleware wsgi css js juicer merging minifying development
Platform: UNKNOWN
Classifier: Development Status :: 4 - Beta
Classifier: Intended Audience :: Developers
Classifier: Programming Language :: Python
Classifier: Topic :: Internet :: WWW/HTTP
Classifier: Topic :: Internet :: WWW/HTTP :: WSGI
Classifier: Topic :: Internet :: WWW/HTTP :: WSGI :: Application
